lib_my_py_package/__init__.py
lib_my_py_package/__main__.py
lib_my_py_package/sub_dir/__init__.py
lib_my_py_package/sub_dir/hello_world.py
lib_my_py_package-0.1.2.dist-info/LICENSE.txt
lib_my_py_package-0.1.2.dist-info/METADATA
lib_my_py_package-0.1.2.dist-info/WHEEL
lib_my_py_package-0.1.2.dist-info/entry_points.txt
lib_my_py_package-0.1.2.dist-info/top_level.txt
lib_my_py_package-0.1.2.dist-info/RECORD
