Metadata-Version: 2.1
Name: lib-my-py-package
Version: 0.1.2
Summary: Print 'Hello World' and echos an argument
Home-page: UNKNOWN
Author: John May
Author-email: 
Maintainer: John May
Maintainer-email: 
License: MIT
Keywords: terminal
Platform: UNKNOWN
Classifier: Environment :: Console
Classifier: Intended Audience :: Developers
Classifier: License :: OSI Approved :: MIT License
Classifier: Operating System :: POSIX :: Linux
Classifier: Programming Language :: Python :: 3
Requires-Python: >=3.6
License-File: LICENSE.txt
